CHANGELOG.md
LICENSE
MANIFEST.in
README.md
setup.cfg
setup.py
pip_services3_mqtt/__init__.py
pip_services3_mqtt.egg-info/PKG-INFO
pip_services3_mqtt.egg-info/SOURCES.txt
pip_services3_mqtt.egg-info/dependency_links.txt
pip_services3_mqtt.egg-info/requires.txt
pip_services3_mqtt.egg-info/top_level.txt
pip_services3_mqtt.egg-info/zip-safe
pip_services3_mqtt/build/DefaultMqttFactory.py
pip_services3_mqtt/build/MqttMessageQueueFactory.py
pip_services3_mqtt/build/__init__.py
pip_services3_mqtt/connect/IMqttMessageListener.py
pip_services3_mqtt/connect/MqttConnection.py
pip_services3_mqtt/connect/MqttConnectionResolver.py
pip_services3_mqtt/connect/MqttSubscription.py
pip_services3_mqtt/connect/__init__.py
pip_services3_mqtt/queues/MqttMessageQueue.py
pip_services3_mqtt/queues/__init__.py
test/build/__init__.py
test/build/test_MqttMessageQueueFactory.py
test/connect/__init__.py
test/connect/test_MqttConnection.py
test/connect/test_MqttConnectionResolver.py
test/queues/MessageQueueFixture.py
test/queues/__init__.py
test/queues/test_MqttMessageQueue.py